regen-docs
setup.py
test
WSGIProxy.egg-info/PKG-INFO
WSGIProxy.egg-info/SOURCES.txt
WSGIProxy.egg-info/dependency_links.txt
WSGIProxy.egg-info/entry_points.txt
WSGIProxy.egg-info/not-zip-safe
WSGIProxy.egg-info/requires.txt
WSGIProxy.egg-info/top_level.txt
docs/code.txt
docs/conf.py
docs/index.txt
docs/license.txt
docs/news.txt
tests/__init__.py
tests/conftest.py
tests/test_exactproxy.txt
wsgiproxy/__init__.py
wsgiproxy/app.py
wsgiproxy/exactproxy.py
wsgiproxy/middleware.py
wsgiproxy/sampleapp.py
wsgiproxy/secretloader.py
wsgiproxy/signature.py
wsgiproxy/spawn.py
wsgiproxy/wsgiapp.py