Metadata-Version: 1.0
Name: WSGIProxy
Version: 0.2
Summary: HTTP proxying tools for WSGI apps
Home-page: http://pythonpaste.org/wsgiproxy/
Author: Ian Bicking
Author-email: ianb@colorstudy.com
License: MIT
Keywords: wsgi paste http proxy
Platform: UNKNOWN
Classifier: Development Status :: 4 - Beta
Classifier: Environment :: Web Environment
Classifier: Framework :: Paste
Classifier: License :: OSI Approved :: MIT License
Classifier: Topic :: Internet :: WWW/HTTP
Classifier: Topic :: Internet :: WWW/HTTP :: WSGI
Classifier: Topic :: Internet :: WWW/HTTP :: WSGI :: Application
Classifier: Topic :: Internet :: WWW/HTTP :: WSGI :: Middleware
